hopconn/__init__.py
hopconn-0.1.dist-info/LICENSE
hopconn-0.1.dist-info/METADATA
hopconn-0.1.dist-info/WHEEL
hopconn-0.1.dist-info/top_level.txt
hopconn-0.1.dist-info/RECORD
