Metadata-Version: 2.1
Name: hopconn
Version: 0.1
Summary: Hop connection test
Author: Muhammad Hamza
License-File: LICENSE
